SGML/__init__.py
SGML/creat_solution.py
SGML/model_adaboost.py
SGML/model_ann.py
SGML/model_bayesianridge.py
SGML/model_ridge.py
SGML/model_svr.py
SGML-2.0.1.dist-info/LICENSE.txt
SGML-2.0.1.dist-info/METADATA
SGML-2.0.1.dist-info/WHEEL
SGML-2.0.1.dist-info/top_level.txt
SGML-2.0.1.dist-info/RECORD
