Metadata-Version: 2.1
Name: SGML
Version: 2.0.1
Summary: A package for solution-guided machine learning method
Home-page: https://github.com/wangrjcn/SGML
Author: Ruijin Wang
Author-email: wangrjcn@shu.edu.cn
Classifier: Programming Language :: Python :: 3
Classifier: License :: OSI Approved :: MIT License
Classifier: Operating System :: OS Independent
Requires-Python: >=3.6
License-File: LICENSE.txt
